reddit_flair_analyzer-1.0.1.dist-info/licenses/LICENSE
redditflairanalyzer/__init__.py
redditflairanalyzer/analyzer.py
redditflairanalyzer/cli.py
redditflairanalyzer/logger.py
redditflairanalyzer/scraper.py
redditflairanalyzer/utils.py
redditflairanalyzer/visualizer.py
tests/__init__.py
tests/test_analyzer.py
tests/test_scraper.py
tests/test_visualizer.py
reddit_flair_analyzer-1.0.1.dist-info/METADATA
reddit_flair_analyzer-1.0.1.dist-info/WHEEL
reddit_flair_analyzer-1.0.1.dist-info/entry_points.txt
reddit_flair_analyzer-1.0.1.dist-info/top_level.txt
reddit_flair_analyzer-1.0.1.dist-info/RECORD
