Metadata-Version: 2.4
Name: reddit-flair-analyzer
Version: 1.0.1
Summary: A professional tool for analyzing which Reddit post flairs have the highest chance of going viral
Home-page: https://github.com/themanojdesai/reddit-flair-analyzer
Author: Manoj Desai
Author-email: themanojdesai@gmail.com
Project-URL: Bug Tracker, https://github.com/themanojdesai/reddit-flair-analyzer/issues
Project-URL: Documentation, https://github.com/themanojdesai/reddit-flair-analyzer/tree/main/docs
Project-URL: Source Code, https://github.com/themanojdesai/reddit-flair-analyzer
Keywords: reddit,data analysis,visualization,flair,social media,analytics,viral,marketing
Classifier: Development Status :: 4 - Beta
Classifier: Intended Audience :: Developers
Classifier: Intended Audience :: Science/Research
Classifier: Intended Audience :: Information Technology
Classifier: License :: OSI Approved :: MIT License
Classifier: Programming Language :: Python :: 3
Classifier: Programming Language :: Python :: 3.7
Classifier: Programming Language :: Python :: 3.8
Classifier: Programming Language :: Python :: 3.9
Classifier: Programming Language :: Python :: 3.10
Classifier: Topic :: Scientific/Engineering :: Information Analysis
Classifier: Topic :: Internet :: WWW/HTTP :: Indexing/Search
Classifier: Operating System :: OS Independent
Requires-Python: >=3.7
License-File: LICENSE
Requires-Dist: praw>=7.0.0
Requires-Dist: pandas>=1.0.0
Requires-Dist: matplotlib>=3.3.0
Requires-Dist: seaborn>=0.11.0
Requires-Dist: numpy>=1.19.0
Requires-Dist: plotly>=5.0.0
Requires-Dist: dash>=2.0.0
Requires-Dist: openpyxl>=3.0.0
Requires-Dist: tqdm>=4.50.0
Requires-Dist: colorlog>=6.0.0
Requires-Dist: tabulate>=0.8.0
Dynamic: author
Dynamic: author-email
Dynamic: classifier
Dynamic: description
Dynamic: description-content-type
Dynamic: home-page
Dynamic: keywords
Dynamic: license-file
Dynamic: project-url
Dynamic: requires-dist
Dynamic: requires-python
Dynamic: summary
